{"surah": 17, "name": "الاسراء", "ayahs": [{"number": 1, "words": [{"display": "بِسْمِ", "match": "بسم"}, {"display": "اللَّهِ", "match": "الله"}, {"display": "الرَّحْمَٰنِ", "match": "الرحمن"}, {"display": "الرَّحِيمِ", "match": "الرحيم"}, {"display": "سُبْحَانَ", "match": "سبحان"}, {"display": "الَّذِي", "match": "الذي"}, {"display": "أَسْرَىٰ", "match": "اسري"}, {"display": "بِعَبْدِهِ", "match": "بعبده"}, {"display": "لَيْلًا", "match": "ليلا"}, {"display": "مِنَ", "match": "من"}, {"display": "الْمَسْجِدِ", "match": "المسجد"}, {"display": "الْحَرَامِ", "match": "الحرام"}, {"display": "إِلَى", "match": "الي"}, {"display": "الْمَسْجِدِ", "match": "المسجد"}, {"display": "الْأَقْصَى", "match": "الاقصي"}, {"display": "الَّذِي", "match": "الذي"}, {"display": "بَارَكْنَا", "match": "باركنا"}, {"display": "حَوْلَهُ", "match": "حوله"}, {"display": "لِنُرِيَهُ", "match": "لنريه"}, {"display": "مِنْ", "match": "من"}, {"display": "آيَاتِنَا", "match": "اياتنا"}, {"display": "ۚ", "match": ""}, {"display": "إِنَّهُ", "match": "انه"}, {"display": "هُوَ", "match": "هو"}, {"display": "السَّمِيعُ", "match": "السميع"}, {"display": "الْبَصِيرُ", "match": "البصير"}]}, {"number": 2, "words": [{"display": "وَآتَيْنَا", "match": "واتينا"}, {"display": "مُوسَى", "match": "موسي"}, {"display": "الْكِتَابَ", "match": "الكتاب"}, {"display": "وَجَعَلْنَاهُ", "match": "وجعلناه"}, {"display": "هُدًى", "match": "هدي"}, {"display": "لِبَنِي", "match": "لبني"}, {"display": "إِسْرَائِيلَ", "match": "اسرائيل"}, {"display": "أَلَّا", "match": "الا"}, {"display": "تَتَّخِذُوا", "match": "تتخذوا"}, {"display": "مِنْ", "match": "من"}, {"display": "دُونِي", "match": "دوني"}, {"display": "وَكِيلًا", "match": "وكيلا"}]}, {"number": 3, "words": [{"display": "ذُرِّيَّةَ", "match": "ذريه"}, {"display": "مَنْ", "match": "من"}, {"display": "حَمَلْنَا", "match": "حملنا"}, {"display": "مَعَ", "match": "مع"}, {"display": "نُوحٍ", "match": "نوح"}, {"display": "ۚ", "match": ""}, {"display": "إِنَّهُ", "match": "انه"}, {"display": "كَانَ", "match": "كان"}, {"display": "عَبْدًا", "match": "عبدا"}, {"display": "شَكُورًا", "match": "شكورا"}]}, {"number": 4, "words": [{"display": "وَقَضَيْنَا", "match": "وقضينا"}, {"display": "إِلَىٰ", "match": "الي"}, {"display": "بَنِي", "match": "بني"}, {"display": "إِسْرَائِيلَ", "match": "اسرائيل"}, {"display": "فِي", "match": "في"}, {"display": "الْكِتَابِ", "match": "الكتاب"}, {"display": "لَتُفْسِدُنَّ", "match": "لتفسدن"}, {"display": "فِي", "match": "في"}, {"display": "الْأَرْضِ", "match": "الارض"}, {"display": "مَرَّتَيْنِ", "match": "مرتين"}, {"display": "وَلَتَعْلُنَّ", "match": "ولتعلن"}, {"display": "عُلُوًّا", "match": "علوا"}, {"display": "كَبِيرًا", "match": "كبيرا"}]}, {"number": 5, "words": [{"display": "فَإِذَا", "match": "فاذا"}, {"display": "جَاءَ", "match": "جاء"}, {"display": "وَعْدُ", "match": "وعد"}, {"display": "أُولَاهُمَا", "match": "اولاهما"}, {"display": "بَعَثْنَا", "match": "بعثنا"}, {"display": "عَلَيْكُمْ", "match": "عليكم"}, {"display": "عِبَادًا", "match": "عبادا"}, {"display": "لَنَا", "match": "لنا"}, {"display": "أُولِي", "match": "اولي"}, {"display": "بَأْسٍ", "match": "باس"}, {"display": "شَدِيدٍ", "match": "شديد"}, {"display": "فَجَاسُوا", "match": "فجاسوا"}, {"display": "خِلَالَ", "match": "خلال"}, {"display": "الدِّيَارِ", "match": "الديار"}, {"display": "ۚ", "match": ""}, {"display": "وَكَانَ", "match": "وكان"}, {"display": "وَعْدًا", "match": "وعدا"}, {"display": "مَفْعُولًا", "match": "مفعولا"}]}, {"number": 6, "words": [{"display": "ثُمَّ", "match": "ثم"}, {"display": "رَدَدْنَا", "match": "رددنا"}, {"display": "لَكُمُ", "match": "لكم"}, {"display": "الْكَرَّةَ", "match": "الكره"}, {"display": "عَلَيْهِمْ", "match": "عليهم"}, {"display": "وَأَمْدَدْنَاكُمْ", "match": "وامددناكم"}, {"display": "بِأَمْوَالٍ", "match": "باموال"}, {"display": "وَبَنِينَ", "match": "وبنين"}, {"display": "وَجَعَلْنَاكُمْ", "match": "وجعلناكم"}, {"display": "أَكْثَرَ", "match": "اكثر"}, {"display": "نَفِيرًا", "match": "نفيرا"}]}, {"number": 7, "words": [{"display": "إِنْ", "match": "ان"}, {"display": "أَحْسَنْتُمْ", "match": "احسنتم"}, {"display": "أَحْسَنْتُمْ", "match": "احسنتم"}, {"display": "لِأَنْفُسِكُمْ", "match": "لانفسكم"}, {"display": "ۖ", "match": ""}, {"display": "وَإِنْ", "match": "وان"}, {"display": "أَسَأْتُمْ", "match": "اساتم"}, {"display": "فَلَهَا", "match": "فلها"}, {"display": "ۚ", "match": ""}, {"display": "فَإِذَا", "match": "فاذا"}, {"display": "جَاءَ", "match": "جاء"}, {"display": "وَعْدُ", "match": "وعد"}, {"display": "الْآخِرَةِ", "match": "الاخره"}, {"display": "لِيَسُوءُوا", "match": "ليسوءوا"}, {"display": "وُجُوهَكُمْ", "match": "وجوهكم"}, {"display": "وَلِيَدْخُلُوا", "match": "وليدخلوا"}, {"display": "الْمَسْجِدَ", "match": "المسجد"}, {"display": "كَمَا", "match": "كما"}, {"display": "دَخَلُوهُ", "match": "دخلوه"}, {"display": "أَوَّلَ", "match": "اول"}, {"display": "مَرَّةٍ", "match": "مره"}, {"display": "وَلِيُتَبِّرُوا", "match": "وليتبروا"}, {"display": "مَا", "match": "ما"}, {"display": "عَلَوْا", "match": "علوا"}, {"display": "تَتْبِيرًا", "match": "تتبيرا"}]}, {"number": 8, "words": [{"display": "عَسَىٰ", "match": "عسي"}, {"display": "رَبُّكُمْ", "match": "ربكم"}, {"display": "أَنْ", "match": "ان"}, {"display": "يَرْحَمَكُمْ", "match": "يرحمكم"}, {"display": "ۚ", "match": ""}, {"display": "وَإِنْ", "match": "وان"}, {"display": "عُدْتُمْ", "match": "عدتم"}, {"display": "عُدْنَا", "match": "عدنا"}, {"display": "ۘ", "match": ""}, {"display": "وَجَعَلْنَا", "match": "وجعلنا"}, {"display": "جَهَنَّمَ", "match": "جهنم"}, {"display": "لِلْكَافِرِينَ", "match": "للكافرين"}, {"display": "حَصِيرًا", "match": "حصيرا"}]}, {"number": 9, "words": [{"display": "إِنَّ", "match": "ان"}, {"display": "هَٰذَا", "match": "هذا"}, {"display": "الْقُرْآنَ", "match": "القران"}, {"display": "يَهْدِي", "match": "يهدي"}, {"display": "لِلَّتِي", "match": "للتي"}, {"display": "هِيَ", "match": "هي"}, {"display": "أَقْوَمُ", "match": "اقوم"}, {"display": "وَيُبَشِّرُ", "match": "ويبشر"}, {"display": "الْمُؤْمِنِينَ", "match": "المؤمنين"}, {"display": "الَّذِينَ", "match": "الذين"}, {"display": "يَعْمَلُونَ", "match": "يعملون"}, {"display": "الصَّالِحَاتِ", "match": "الصالحات"}, {"display": "أَنَّ", "match": "ان"}, {"display": "لَهُمْ", "match": "لهم"}, {"display": "أَجْرًا", "match": "اجرا"}, {"display": "كَبِيرًا", "match": "كبيرا"}]}, {"number": 10, "words": [{"display": "وَأَنَّ", "match": "وان"}, {"display": "الَّذِينَ", "match": "الذين"}, {"display": "لَا", "match": "لا"}, {"display": "يُؤْمِنُونَ", "match": "يؤمنون"}, {"display": "بِالْآخِرَةِ", "match": "بالاخره"}, {"display": "أَعْتَدْنَا", "match": "اعتدنا"}, {"display": "لَهُمْ", "match": "لهم"}, {"display": "عَذَابًا", "match": "عذابا"}, {"display": "أَلِيمًا", "match": "اليما"}]}, {"number": 11, "words": [{"display": "وَيَدْعُ", "match": "ويدع"}, {"display": "الْإِنْسَانُ", "match": "الانسان"}, {"display": "بِالشَّرِّ", "match": "بالشر"}, {"display": "دُعَاءَهُ", "match": "دعاءه"}, {"display": "بِالْخَيْرِ", "match": "بالخير"}, {"display": "ۖ", "match": ""}, {"display": "وَكَانَ", "match": "وكان"}, {"display": "الْإِنْسَانُ", "match": "الانسان"}, {"display": "عَجُولًا", "match": "عجولا"}]}, {"number": 12, "words": [{"display": "وَجَعَلْنَا", "match": "وجعلنا"}, {"display": "اللَّيْلَ", "match": "الليل"}, {"display": "وَالنَّهَارَ", "match": "والنهار"}, {"display": "آيَتَيْنِ", "match": "ايتين"}, {"display": "ۖ", "match": ""}, {"display": "فَمَحَوْنَا", "match": "فمحونا"}, {"display": "آيَةَ", "match": "ايه"}, {"display": "اللَّيْلِ", "match": "الليل"}, {"display": "وَجَعَلْنَا", "match": "وجعلنا"}, {"display": "آيَةَ", "match": "ايه"}, {"display": "النَّهَارِ", "match": "النهار"}, {"display": "مُبْصِرَةً", "match": "مبصره"}, {"display": "لِتَبْتَغُوا", "match": "لتبتغوا"}, {"display": "فَضْلًا", "match": "فضلا"}, {"display": "مِنْ", "match": "من"}, {"display": "رَبِّكُمْ", "match": "ربكم"}, {"display": "وَلِتَعْلَمُوا", "match": "ولتعلموا"}, {"display": "عَدَدَ", "match": "عدد"}, {"display": "السِّنِينَ", "match": "السنين"}, {"display": "وَالْحِسَابَ", "match": "والحساب"}, {"display": "ۚ", "match": ""}, {"display": "وَكُلَّ", "match": "وكل"}, {"display": "شَيْءٍ", "match": "شيء"}, {"display": "فَصَّلْنَاهُ", "match": "فصلناه"}, {"display": "تَفْصِيلًا", "match": "تفصيلا"}]}, {"number": 13, "words": [{"display": "وَكُلَّ", "match": "وكل"}, {"display": "إِنْسَانٍ", "match": "انسان"}, {"display": "أَلْزَمْنَاهُ", "match": "الزمناه"}, {"display": "طَائِرَهُ", "match": "طائره"}, {"display": "فِي", "match": "في"}, {"display": "عُنُقِهِ", "match": "عنقه"}, {"display": "ۖ", "match": ""}, {"display": "وَنُخْرِجُ", "match": "ونخرج"}, {"display": "لَهُ", "match": "له"}, {"display": "يَوْمَ", "match": "يوم"}, {"display": "الْقِيَامَةِ", "match": "القيامه"}, {"display": "كِتَابًا", "match": "كتابا"}, {"display": "يَلْقَاهُ", "match": "يلقاه"}, {"display": "مَنْشُورًا", "match": "منشورا"}]}, {"number": 14, "words": [{"display": "اقْرَأْ", "match": "اقرا"}, {"display": "كِتَابَكَ", "match": "كتابك"}, {"display": "كَفَىٰ", "match": "كفي"}, {"display": "بِنَفْسِكَ", "match": "بنفسك"}, {"display": "الْيَوْمَ", "match": "اليوم"}, {"display": "عَلَيْكَ", "match": "عليك"}, {"display": "حَسِيبًا", "match": "حسيبا"}]}, {"number": 15, "words": [{"display": "مَنِ", "match": "من"}, {"display": "اهْتَدَىٰ", "match": "اهتدي"}, {"display": "فَإِنَّمَا", "match": "فانما"}, {"display": "يَهْتَدِي", "match": "يهتدي"}, {"display": "لِنَفْسِهِ", "match": "لنفسه"}, {"display": "ۖ", "match": ""}, {"display": "وَمَنْ", "match": "ومن"}, {"display": "ضَلَّ", "match": "ضل"}, {"display": "فَإِنَّمَا", "match": "فانما"}, {"display": "يَضِلُّ", "match": "يضل"}, {"display": "عَلَيْهَا", "match": "عليها"}, {"display": "ۚ", "match": ""}, {"display": "وَلَا", "match": "ولا"}, {"display": "تَزِرُ", "match": "تزر"}, {"display": "وَازِرَةٌ", "match": "وازره"}, {"display": "وِزْرَ", "match": "وزر"}, {"display": "أُخْرَىٰ", "match": "اخري"}, {"display": "ۗ", "match": ""}, {"display": "وَمَا", "match": "وما"}, {"display": "كُنَّا", "match": "كنا"}, {"display": "مُعَذِّبِينَ", "match": "معذبين"}, {"display": "حَتَّىٰ", "match": "حتي"}, {"display": "نَبْعَثَ", "match": "نبعث"}, {"display": "رَسُولًا", "match": "رسولا"}]}, {"number": 16, "words": [{"display": "وَإِذَا", "match": "واذا"}, {"display": "أَرَدْنَا", "match": "اردنا"}, {"display": "أَنْ", "match": "ان"}, {"display": "نُهْلِكَ", "match": "نهلك"}, {"display": "قَرْيَةً", "match": "قريه"}, {"display": "أَمَرْنَا", "match": "امرنا"}, {"display": "مُتْرَفِيهَا", "match": "مترفيها"}, {"display": "فَفَسَقُوا", "match": "ففسقوا"}, {"display": "فِيهَا", "match": "فيها"}, {"display": "فَحَقَّ", "match": "فحق"}, {"display": "عَلَيْهَا", "match": "عليها"}, {"display": "الْقَوْلُ", "match": "القول"}, {"display": "فَدَمَّرْنَاهَا", "match": "فدمرناها"}, {"display": "تَدْمِيرًا", "match": "تدميرا"}]}, {"number": 17, "words": [{"display": "وَكَمْ", "match": "وكم"}, {"display": "أَهْلَكْنَا", "match": "اهلكنا"}, {"display": "مِنَ", "match": "من"}, {"display": "الْقُرُونِ", "match": "القرون"}, {"display": "مِنْ", "match": "من"}, {"display": "بَعْدِ", "match": "بعد"}, {"display": "نُوحٍ", "match": "نوح"}, {"display": "ۗ", "match": ""}, {"display": "وَكَفَىٰ", "match": "وكفي"}, {"display": "بِرَبِّكَ", "match": "بربك"}, {"display": "بِذُنُوبِ", "match": "بذنوب"}, {"display": "عِبَادِهِ", "match": "عباده"}, {"display": "خَبِيرًا", "match": "خبيرا"}, {"display": "بَصِيرًا", "match": "بصيرا"}]}, {"number": 18, "words": [{"display": "مَنْ", "match": "من"}, {"display": "كَانَ", "match": "كان"}, {"display": "يُرِيدُ", "match": "يريد"}, {"display": "الْعَاجِلَةَ", "match": "العاجله"}, {"display": "عَجَّلْنَا", "match": "عجلنا"}, {"display": "لَهُ", "match": "له"}, {"display": "فِيهَا", "match": "فيها"}, {"display": "مَا", "match": "ما"}, {"display": "نَشَاءُ", "match": "نشاء"}, {"display": "لِمَنْ", "match": "لمن"}, {"display": "نُرِيدُ", "match": "نريد"}, {"display": "ثُمَّ", "match": "ثم"}, {"display": "جَعَلْنَا", "match": "جعلنا"}, {"display": "لَهُ", "match": "له"}, {"display": "جَهَنَّمَ", "match": "جهنم"}, {"display": "يَصْلَاهَا", "match": "يصلاها"}, {"display": "مَذْمُومًا", "match": "مذموما"}, {"display": "مَدْحُورًا", "match": "مدحورا"}]}, {"number": 19, "words": [{"display": "وَمَنْ", "match": "ومن"}, {"display": "أَرَادَ", "match": "اراد"}, {"display": "الْآخِرَةَ", "match": "الاخره"}, {"display": "وَسَعَىٰ", "match": "وسعي"}, {"display": "لَهَا", "match": "لها"}, {"display": "سَعْيَهَا", "match": "سعيها"}, {"display": "وَهُوَ", "match": "وهو"}, {"display": "مُؤْمِنٌ", "match": "مؤمن"}, {"display": "فَأُولَٰئِكَ", "match": "فاولئك"}, {"display": "كَانَ", "match": "كان"}, {"display": "سَعْيُهُمْ", "match": "سعيهم"}, {"display": "مَشْكُورًا", "match": "مشكورا"}]}, {"number": 20, "words": [{"display": "كُلًّا", "match": "كلا"}, {"display": "نُمِدُّ", "match": "نمد"}, {"display": "هَٰؤُلَاءِ", "match": "هؤلاء"}, {"display": "وَهَٰؤُلَاءِ", "match": "وهؤلاء"}, {"display": "مِنْ", "match": "من"}, {"display": "عَطَاءِ", "match": "عطاء"}, {"display": "رَبِّكَ", "match": "ربك"}, {"display": "ۚ", "match": ""}, {"display": "وَمَا", "match": "وما"}, {"display": "كَانَ", "match": "كان"}, {"display": "عَطَاءُ", "match": "عطاء"}, {"display": "رَبِّكَ", "match": "ربك"}, {"display": "مَحْظُورًا", "match": "محظورا"}]}, {"number": 21, "words": [{"display": "انْظُرْ", "match": "انظر"}, {"display": "كَيْفَ", "match": "كيف"}, {"display": "فَضَّلْنَا", "match": "فضلنا"}, {"display": "بَعْضَهُمْ", "match": "بعضهم"}, {"display": "عَلَىٰ", "match": "علي"}, {"display": "بَعْضٍ", "match": "بعض"}, {"display": "ۚ", "match": ""}, {"display": "وَلَلْآخِرَةُ", "match": "وللاخره"}, {"display": "أَكْبَرُ", "match": "اكبر"}, {"display": "دَرَجَاتٍ", "match": "درجات"}, {"display": "وَأَكْبَرُ", "match": "واكبر"}, {"display": "تَفْضِيلًا", "match": "تفضيلا"}]}, {"number": 22, "words": [{"display": "لَا", "match": "لا"}, {"display": "تَجْعَلْ", "match": "تجعل"}, {"display": "مَعَ", "match": "مع"}, {"display": "اللَّهِ", "match": "الله"}, {"display": "إِلَٰهًا", "match": "الها"}, {"display": "آخَرَ", "match": "اخر"}, {"display": "فَتَقْعُدَ", "match": "فتقعد"}, {"display": "مَذْمُومًا", "match": "مذموما"}, {"display": "مَخْذُولًا", "match": "مخذولا"}]}, {"number": 23, "words": [{"display": "وَقَضَىٰ", "match": "وقضي"}, {"display": "رَبُّكَ", "match": "ربك"}, {"display": "أَلَّا", "match": "الا"}, {"display": "تَعْبُدُوا", "match": "تعبدوا"}, {"display": "إِلَّا", "match": "الا"}, {"display": "إِيَّاهُ", "match": "اياه"}, {"display": "وَبِالْوَالِدَيْنِ", "match": "وبالوالدين"}, {"display": "إِحْسَانًا", "match": "احسانا"}, {"display": "ۚ", "match": ""}, {"display": "إِمَّا", "match": "اما"}, {"display": "يَبْلُغَنَّ", "match": "يبلغن"}, {"display": "عِنْدَكَ", "match": "عندك"}, {"display": "الْكِبَرَ", "match": "الكبر"}, {"display": "أَحَدُهُمَا", "match": "احدهما"}, {"display": "أَوْ", "match": "او"}, {"display": "كِلَاهُمَا", "match": "كلاهما"}, {"display": "فَلَا", "match": "فلا"}, {"display": "تَقُلْ", "match": "تقل"}, {"display": "لَهُمَا", "match": "لهما"}, {"display": "أُفٍّ", "match": "اف"}, {"display": "وَلَا", "match": "ولا"}, {"display": "تَنْهَرْهُمَا", "match": "تنهرهما"}, {"display": "وَقُلْ", "match": "وقل"}, {"display": "لَهُمَا", "match": "لهما"}, {"display": "قَوْلًا", "match": "قولا"}, {"display": "كَرِيمًا", "match": "كريما"}]}, {"number": 24, "words": [{"display": "وَاخْفِضْ", "match": "واخفض"}, {"display": "لَهُمَا", "match": "لهما"}, {"display": "جَنَاحَ", "match": "جناح"}, {"display": "الذُّلِّ", "match": "الذل"}, {"display": "مِنَ", "match": "من"}, {"display": "الرَّحْمَةِ", "match": "الرحمه"}, {"display": "وَقُلْ", "match": "وقل"}, {"display": "رَبِّ", "match": "رب"}, {"display": "ارْحَمْهُمَا", "match": "ارحمهما"}, {"display": "كَمَا", "match": "كما"}, {"display": "رَبَّيَانِي", "match": "ربياني"}, {"display": "صَغِيرًا", "match": "صغيرا"}]}, {"number": 25, "words": [{"display": "رَبُّكُمْ", "match": "ربكم"}, {"display": "أَعْلَمُ", "match": "اعلم"}, {"display": "بِمَا", "match": "بما"}, {"display": "فِي", "match": "في"}, {"display": "نُفُوسِكُمْ", "match": "نفوسكم"}, {"display": "ۚ", "match": ""}, {"display": "إِنْ", "match": "ان"}, {"display": "تَكُونُوا", "match": "تكونوا"}, {"display": "صَالِحِينَ", "match": "صالحين"}, {"display": "فَإِنَّهُ", "match": "فانه"}, {"display": "كَانَ", "match": "كان"}, {"display": "لِلْأَوَّابِينَ", "match": "للاوابين"}, {"display": "غَفُورًا", "match": "غفورا"}]}, {"number": 26, "words": [{"display": "وَآتِ", "match": "وات"}, {"display": "ذَا", "match": "ذا"}, {"display": "الْقُرْبَىٰ", "match": "القربي"}, {"display": "حَقَّهُ", "match": "حقه"}, {"display": "وَالْمِسْكِينَ", "match": "والمسكين"}, {"display": "وَابْنَ", "match": "وابن"}, {"display": "السَّبِيلِ", "match": "السبيل"}, {"display": "وَلَا", "match": "ولا"}, {"display": "تُبَذِّرْ", "match": "تبذر"}, {"display": "تَبْذِيرًا", "match": "تبذيرا"}]}, {"number": 27, "words": [{"display": "إِنَّ", "match": "ان"}, {"display": "الْمُبَذِّرِينَ", "match": "المبذرين"}, {"display": "كَانُوا", "match": "كانوا"}, {"display": "إِخْوَانَ", "match": "اخوان"}, {"display": "الشَّيَاطِينِ", "match": "الشياطين"}, {"display": "ۖ", "match": ""}, {"display": "وَكَانَ", "match": "وكان"}, {"display": "الشَّيْطَانُ", "match": "الشيطان"}, {"display": "لِرَبِّهِ", "match": "لربه"}, {"display": "كَفُورًا", "match": "كفورا"}]}, {"number": 28, "words": [{"display": "وَإِمَّا", "match": "واما"}, {"display": "تُعْرِضَنَّ", "match": "تعرضن"}, {"display": "عَنْهُمُ", "match": "عنهم"}, {"display": "ابْتِغَاءَ", "match": "ابتغاء"}, {"display": "رَحْمَةٍ", "match": "رحمه"}, {"display": "مِنْ", "match": "من"}, {"display": "رَبِّكَ", "match": "ربك"}, {"display": "تَرْجُوهَا", "match": "ترجوها"}, {"display": "فَقُلْ", "match": "فقل"}, {"display": "لَهُمْ", "match": "لهم"}, {"display": "قَوْلًا", "match": "قولا"}, {"display": "مَيْسُورًا", "match": "ميسورا"}]}, {"number": 29, "words": [{"display": "وَلَا", "match": "ولا"}, {"display": "تَجْعَلْ", "match": "تجعل"}, {"display": "يَدَكَ", "match": "يدك"}, {"display": "مَغْلُولَةً", "match": "مغلوله"}, {"display": "إِلَىٰ", "match": "الي"}, {"display": "عُنُقِكَ", "match": "عنقك"}, {"display": "وَلَا", "match": "ولا"}, {"display": "تَبْسُطْهَا", "match": "تبسطها"}, {"display": "كُلَّ", "match": "كل"}, {"display": "الْبَسْطِ", "match": "البسط"}, {"display": "فَتَقْعُدَ", "match": "فتقعد"}, {"display": "مَلُومًا", "match": "ملوما"}, {"display": "مَحْسُورًا", "match": "محسورا"}]}, {"number": 30, "words": [{"display": "إِنَّ", "match": "ان"}, {"display": "رَبَّكَ", "match": "ربك"}, {"display": "يَبْسُطُ", "match": "يبسط"}, {"display": "الرِّزْقَ", "match": "الرزق"}, {"display": "لِمَنْ", "match": "لمن"}, {"display": "يَشَاءُ", "match": "يشاء"}, {"display": "وَيَقْدِرُ", "match": "ويقدر"}, {"display": "ۚ", "match": ""}, {"display": "إِنَّهُ", "match": "انه"}, {"display": "كَانَ", "match": "كان"}, {"display": "بِعِبَادِهِ", "match": "بعباده"}, {"display": "خَبِيرًا", "match": "خبيرا"}, {"display": "بَصِيرًا", "match": "بصيرا"}]}, {"number": 31, "words": [{"display": "وَلَا", "match": "ولا"}, {"display": "تَقْتُلُوا", "match": "تقتلوا"}, {"display": "أَوْلَادَكُمْ", "match": "اولادكم"}, {"display": "خَشْيَةَ", "match": "خشيه"}, {"display": "إِمْلَاقٍ", "match": "املاق"}, {"display": "ۖ", "match": ""}, {"display": "نَحْنُ", "match": "نحن"}, {"display": "نَرْزُقُهُمْ", "match": "نرزقهم"}, {"display": "وَإِيَّاكُمْ", "match": "واياكم"}, {"display": "ۚ", "match": ""}, {"display": "إِنَّ", "match": "ان"}, {"display": "قَتْلَهُمْ", "match": "قتلهم"}, {"display": "كَانَ", "match": "كان"}, {"display": "خِطْئًا", "match": "خطئا"}, {"display": "كَبِيرًا", "match": "كبيرا"}]}, {"number": 32, "words": [{"display": "وَلَا", "match": "ولا"}, {"display": "تَقْرَبُوا", "match": "تقربوا"}, {"display": "الزِّنَا", "match": "الزنا"}, {"display": "ۖ", "match": ""}, {"display": "إِنَّهُ", "match": "انه"}, {"display": "كَانَ", "match": "كان"}, {"display": "فَاحِشَةً", "match": "فاحشه"}, {"display": "وَسَاءَ", "match": "وساء"}, {"display": "سَبِيلًا", "match": "سبيلا"}]}, {"number": 33, "words": [{"display": "وَلَا", "match": "ولا"}, {"display": "تَقْتُلُوا", "match": "تقتلوا"}, {"display": "النَّفْسَ", "match": "النفس"}, {"display": "الَّتِي", "match": "التي"}, {"display": "حَرَّمَ", "match": "حرم"}, {"display": "اللَّهُ", "match": "الله"}, {"display": "إِلَّا", "match": "الا"}, {"display": "بِالْحَقِّ", "match": "بالحق"}, {"display": "ۗ", "match": ""}, {"display": "وَمَنْ", "match": "ومن"}, {"display": "قُتِلَ", "match": "قتل"}, {"display": "مَظْلُومًا", "match": "مظلوما"}, {"display": "فَقَدْ", "match": "فقد"}, {"display": "جَعَلْنَا", "match": "جعلنا"}, {"display": "لِوَلِيِّهِ", "match": "لوليه"}, {"display": "سُلْطَانًا", "match": "سلطانا"}, {"display": "فَلَا", "match": "فلا"}, {"display": "يُسْرِفْ", "match": "يسرف"}, {"display": "فِي", "match": "في"}, {"display": "الْقَتْلِ", "match": "القتل"}, {"display": "ۖ", "match": ""}, {"display": "إِنَّهُ", "match": "انه"}, {"display": "كَانَ", "match": "كان"}, {"display": "مَنْصُورًا", "match": "منصورا"}]}, {"number": 34, "words": [{"display": "وَلَا", "match": "ولا"}, {"display": "تَقْرَبُوا", "match": "تقربوا"}, {"display": "مَالَ", "match": "مال"}, {"display": "الْيَتِيمِ", "match": "اليتيم"}, {"display": "إِلَّا", "match": "الا"}, {"display": "بِالَّتِي", "match": "بالتي"}, {"display": "هِيَ", "match": "هي"}, {"display": "أَحْسَنُ", "match": "احسن"}, {"display": "حَتَّىٰ", "match": "حتي"}, {"display": "يَبْلُغَ", "match": "يبلغ"}, {"display": "أَشُدَّهُ", "match": "اشده"}, {"display": "ۚ", "match": ""}, {"display": "وَأَوْفُوا", "match": "واوفوا"}, {"display": "بِالْعَهْدِ", "match": "بالعهد"}, {"display": "ۖ", "match": ""}, {"display": "إِنَّ", "match": "ان"}, {"display": "الْعَهْدَ", "match": "العهد"}, {"display": "كَانَ", "match": "كان"}, {"display": "مَسْئُولًا", "match": "مسئولا"}]}, {"number": 35, "words": [{"display": "وَأَوْفُوا", "match": "واوفوا"}, {"display": "الْكَيْلَ", "match": "الكيل"}, {"display": "إِذَا", "match": "اذا"}, {"display": "كِلْتُمْ", "match": "كلتم"}, {"display": "وَزِنُوا", "match": "وزنوا"}, {"display": "بِالْقِسْطَاسِ", "match": "بالقسطاس"}, {"display": "الْمُسْتَقِيمِ", "match": "المستقيم"}, {"display": "ۚ", "match": ""}, {"display": "ذَٰلِكَ", "match": "ذلك"}, {"display": "خَيْرٌ", "match": "خير"}, {"display": "وَأَحْسَنُ", "match": "واحسن"}, {"display": "تَأْوِيلًا", "match": "تاويلا"}]}, {"number": 36, "words": [{"display": "وَلَا", "match": "ولا"}, {"display": "تَقْفُ", "match": "تقف"}, {"display": "مَا", "match": "ما"}, {"display": "لَيْسَ", "match": "ليس"}, {"display": "لَكَ", "match": "لك"}, {"display": "بِهِ", "match": "به"}, {"display": "عِلْمٌ", "match": "علم"}, {"display": "ۚ", "match": ""}, {"display": "إِنَّ", "match": "ان"}, {"display": "السَّمْعَ", "match": "السمع"}, {"display": "وَالْبَصَرَ", "match": "والبصر"}, {"display": "وَالْفُؤَادَ", "match": "والفؤاد"}, {"display": "كُلُّ", "match": "كل"}, {"display": "أُولَٰئِكَ", "match": "اولئك"}, {"display": "كَانَ", "match": "كان"}, {"display": "عَنْهُ", "match": "عنه"}, {"display": "مَسْئُولًا", "match": "مسئولا"}]}, {"number": 37, "words": [{"display": "وَلَا", "match": "ولا"}, {"display": "تَمْشِ", "match": "تمش"}, {"display": "فِي", "match": "في"}, {"display": "الْأَرْضِ", "match": "الارض"}, {"display": "مَرَحًا", "match": "مرحا"}, {"display": "ۖ", "match": ""}, {"display": "إِنَّكَ", "match": "انك"}, {"display": "لَنْ", "match": "لن"}, {"display": "تَخْرِقَ", "match": "تخرق"}, {"display": "الْأَرْضَ", "match": "الارض"}, {"display": "وَلَنْ", "match": "ولن"}, {"display": "تَبْلُغَ", "match": "تبلغ"}, {"display": "الْجِبَالَ", "match": "الجبال"}, {"display": "طُولًا", "match": "طولا"}]}, {"number": 38, "words": [{"display": "كُلُّ", "match": "كل"}, {"display": "ذَٰلِكَ", "match": "ذلك"}, {"display": "كَانَ", "match": "كان"}, {"display": "سَيِّئُهُ", "match": "سيئه"}, {"display": "عِنْدَ", "match": "عند"}, {"display": "رَبِّكَ", "match": "ربك"}, {"display": "مَكْرُوهًا", "match": "مكروها"}]}, {"number": 39, "words": [{"display": "ذَٰلِكَ", "match": "ذلك"}, {"display": "مِمَّا", "match": "مما"}, {"display": "أَوْحَىٰ", "match": "اوحي"}, {"display": "إِلَيْكَ", "match": "اليك"}, {"display": "رَبُّكَ", "match": "ربك"}, {"display": "مِنَ", "match": "من"}, {"display": "الْحِكْمَةِ", "match": "الحكمه"}, {"display": "ۗ", "match": ""}, {"display": "وَلَا", "match": "ولا"}, {"display": "تَجْعَلْ", "match": "تجعل"}, {"display": "مَعَ", "match": "مع"}, {"display": "اللَّهِ", "match": "الله"}, {"display": "إِلَٰهًا", "match": "الها"}, {"display": "آخَرَ", "match": "اخر"}, {"display": "فَتُلْقَىٰ", "match": "فتلقي"}, {"display": "فِي", "match": "في"}, {"display": "جَهَنَّمَ", "match": "جهنم"}, {"display": "مَلُومًا", "match": "ملوما"}, {"display": "مَدْحُورًا", "match": "مدحورا"}]}, {"number": 40, "words": [{"display": "أَفَأَصْفَاكُمْ", "match": "افاصفاكم"}, {"display": "رَبُّكُمْ", "match": "ربكم"}, {"display": "بِالْبَنِينَ", "match": "بالبنين"}, {"display": "وَاتَّخَذَ", "match": "واتخذ"}, {"display": "مِنَ", "match": "من"}, {"display": "الْمَلَائِكَةِ", "match": "الملائكه"}, {"display": "إِنَاثًا", "match": "اناثا"}, {"display": "ۚ", "match": ""}, {"display": "إِنَّكُمْ", "match": "انكم"}, {"display": "لَتَقُولُونَ", "match": "لتقولون"}, {"display": "قَوْلًا", "match": "قولا"}, {"display": "عَظِيمًا", "match": "عظيما"}]}, {"number": 41, "words": [{"display": "وَلَقَدْ", "match": "ولقد"}, {"display": "صَرَّفْنَا", "match": "صرفنا"}, {"display": "فِي", "match": "في"}, {"display": "هَٰذَا", "match": "هذا"}, {"display": "الْقُرْآنِ", "match": "القران"}, {"display": "لِيَذَّكَّرُوا", "match": "ليذكروا"}, {"display": "وَمَا", "match": "وما"}, {"display": "يَزِيدُهُمْ", "match": "يزيدهم"}, {"display": "إِلَّا", "match": "الا"}, {"display": "نُفُورًا", "match": "نفورا"}]}, {"number": 42, "words": [{"display": "قُلْ", "match": "قل"}, {"display": "لَوْ", "match": "لو"}, {"display": "كَانَ", "match": "كان"}, {"display": "مَعَهُ", "match": "معه"}, {"display": "آلِهَةٌ", "match": "الهه"}, {"display": "كَمَا", "match": "كما"}, {"display": "يَقُولُونَ", "match": "يقولون"}, {"display": "إِذًا", "match": "اذا"}, {"display": "لَابْتَغَوْا", "match": "لابتغوا"}, {"display": "إِلَىٰ", "match": "الي"}, {"display": "ذِي", "match": "ذي"}, {"display": "الْعَرْشِ", "match": "العرش"}, {"display": "سَبِيلًا", "match": "سبيلا"}]}, {"number": 43, "words": [{"display": "سُبْحَانَهُ", "match": "سبحانه"}, {"display": "وَتَعَالَىٰ", "match": "وتعالي"}, {"display": "عَمَّا", "match": "عما"}, {"display": "يَقُولُونَ", "match": "يقولون"}, {"display": "عُلُوًّا", "match": "علوا"}, {"display": "كَبِيرًا", "match": "كبيرا"}]}, {"number": 44, "words": [{"display": "تُسَبِّحُ", "match": "تسبح"}, {"display": "لَهُ", "match": "له"}, {"display": "السَّمَاوَاتُ", "match": "السماوات"}, {"display": "السَّبْعُ", "match": "السبع"}, {"display": "وَالْأَرْضُ", "match": "والارض"}, {"display": "وَمَنْ", "match": "ومن"}, {"display": "فِيهِنَّ", "match": "فيهن"}, {"display": "ۚ", "match": ""}, {"display": "وَإِنْ", "match": "وان"}, {"display": "مِنْ", "match": "من"}, {"display": "شَيْءٍ", "match": "شيء"}, {"display": "إِلَّا", "match": "الا"}, {"display": "يُسَبِّحُ", "match": "يسبح"}, {"display": "بِحَمْدِهِ", "match": "بحمده"}, {"display": "وَلَٰكِنْ", "match": "ولكن"}, {"display": "لَا", "match": "لا"}, {"display": "تَفْقَهُونَ", "match": "تفقهون"}, {"display": "تَسْبِيحَهُمْ", "match": "تسبيحهم"}, {"display": "ۗ", "match": ""}, {"display": "إِنَّهُ", "match": "انه"}, {"display": "كَانَ", "match": "كان"}, {"display": "حَلِيمًا", "match": "حليما"}, {"display": "غَفُورًا", "match": "غفورا"}]}, {"number": 45, "words": [{"display": "وَإِذَا", "match": "واذا"}, {"display": "قَرَأْتَ", "match": "قرات"}, {"display": "الْقُرْآنَ", "match": "القران"}, {"display": "جَعَلْنَا", "match": "جعلنا"}, {"display": "بَيْنَكَ", "match": "بينك"}, {"display": "وَبَيْنَ", "match": "وبين"}, {"display": "الَّذِينَ", "match": "الذين"}, {"display": "لَا", "match": "لا"}, {"display": "يُؤْمِنُونَ", "match": "يؤمنون"}, {"display": "بِالْآخِرَةِ", "match": "بالاخره"}, {"display": "حِجَابًا", "match": "حجابا"}, {"display": "مَسْتُورًا", "match": "مستورا"}]}, {"number": 46, "words": [{"display": "وَجَعَلْنَا", "match": "وجعلنا"}, {"display": "عَلَىٰ", "match": "علي"}, {"display": "قُلُوبِهِمْ", "match": "قلوبهم"}, {"display": "أَكِنَّةً", "match": "اكنه"}, {"display": "أَنْ", "match": "ان"}, {"display": "يَفْقَهُوهُ", "match": "يفقهوه"}, {"display": "وَفِي", "match": "وفي"}, {"display": "آذَانِهِمْ", "match": "اذانهم"}, {"display": "وَقْرًا", "match": "وقرا"}, {"display": "ۚ", "match": ""}, {"display": "وَإِذَا", "match": "واذا"}, {"display": "ذَكَرْتَ", "match": "ذكرت"}, {"display": "رَبَّكَ", "match": "ربك"}, {"display": "فِي", "match": "في"}, {"display": "الْقُرْآنِ", "match": "القران"}, {"display": "وَحْدَهُ", "match": "وحده"}, {"display": "وَلَّوْا", "match": "ولوا"}, {"display": "عَلَىٰ", "match": "علي"}, {"display": "أَدْبَارِهِمْ", "match": "ادبارهم"}, {"display": "نُفُورًا", "match": "نفورا"}]}, {"number": 47, "words": [{"display": "نَحْنُ", "match": "نحن"}, {"display": "أَعْلَمُ", "match": "اعلم"}, {"display": "بِمَا", "match": "بما"}, {"display": "يَسْتَمِعُونَ", "match": "يستمعون"}, {"display": "بِهِ", "match": "به"}, {"display": "إِذْ", "match": "اذ"}, {"display": "يَسْتَمِعُونَ", "match": "يستمعون"}, {"display": "إِلَيْكَ", "match": "اليك"}, {"display": "وَإِذْ", "match": "واذ"}, {"display": "هُمْ", "match": "هم"}, {"display": "نَجْوَىٰ", "match": "نجوي"}, {"display": "إِذْ", "match": "اذ"}, {"display": "يَقُولُ", "match": "يقول"}, {"display": "الظَّالِمُونَ", "match": "الظالمون"}, {"display": "إِنْ", "match": "ان"}, {"display": "تَتَّبِعُونَ", "match": "تتبعون"}, {"display": "إِلَّا", "match": "الا"}, {"display": "رَجُلًا", "match": "رجلا"}, {"display": "مَسْحُورًا", "match": "مسحورا"}]}, {"number": 48, "words": [{"display": "انْظُرْ", "match": "انظر"}, {"display": "كَيْفَ", "match": "كيف"}, {"display": "ضَرَبُوا", "match": "ضربوا"}, {"display": "لَكَ", "match": "لك"}, {"display": "الْأَمْثَالَ", "match": "الامثال"}, {"display": "فَضَلُّوا", "match": "فضلوا"}, {"display": "فَلَا", "match": "فلا"}, {"display": "يَسْتَطِيعُونَ", "match": "يستطيعون"}, {"display": "سَبِيلًا", "match": "سبيلا"}]}, {"number": 49, "words": [{"display": "وَقَالُوا", "match": "وقالوا"}, {"display": "أَإِذَا", "match": "ااذا"}, {"display": "كُنَّا", "match": "كنا"}, {"display": "عِظَامًا", "match": "عظاما"}, {"display": "وَرُفَاتًا", "match": "ورفاتا"}, {"display": "أَإِنَّا", "match": "اانا"}, {"display": "لَمَبْعُوثُونَ", "match": "لمبعوثون"}, {"display": "خَلْقًا", "match": "خلقا"}, {"display": "جَدِيدًا", "match": "جديدا"}]}, {"number": 50, "words": [{"display": "قُلْ", "match": "قل"}, {"display": "كُونُوا", "match": "كونوا"}, {"display": "حِجَارَةً", "match": "حجاره"}, {"display": "أَوْ", "match": "او"}, {"display": "حَدِيدًا", "match": "حديدا"}]}, {"number": 51, "words": [{"display": "أَوْ", "match": "او"}, {"display": "خَلْقًا", "match": "خلقا"}, {"display": "مِمَّا", "match": "مما"}, {"display": "يَكْبُرُ", "match": "يكبر"}, {"display": "فِي", "match": "في"}, {"display": "صُدُورِكُمْ", "match": "صدوركم"}, {"display": "ۚ", "match": ""}, {"display": "فَسَيَقُولُونَ", "match": "فسيقولون"}, {"display": "مَنْ", "match": "من"}, {"display": "يُعِيدُنَا", "match": "يعيدنا"}, {"display": "ۖ", "match": ""}, {"display": "قُلِ", "match": "قل"}, {"display": "الَّذِي", "match": "الذي"}, {"display": "فَطَرَكُمْ", "match": "فطركم"}, {"display": "أَوَّلَ", "match": "اول"}, {"display": "مَرَّةٍ", "match": "مره"}, {"display": "ۚ", "match": ""}, {"display": "فَسَيُنْغِضُونَ", "match": "فسينغضون"}, {"display": "إِلَيْكَ", "match": "اليك"}, {"display": "رُءُوسَهُمْ", "match": "رءوسهم"}, {"display": "وَيَقُولُونَ", "match": "ويقولون"}, {"display": "مَتَىٰ", "match": "متي"}, {"display": "هُوَ", "match": "هو"}, {"display": "ۖ", "match": ""}, {"display": "قُلْ", "match": "قل"}, {"display": "عَسَىٰ", "match": "عسي"}, {"display": "أَنْ", "match": "ان"}, {"display": "يَكُونَ", "match": "يكون"}, {"display": "قَرِيبًا", "match": "قريبا"}]}, {"number": 52, "words": [{"display": "يَوْمَ", "match": "يوم"}, {"display": "يَدْعُوكُمْ", "match": "يدعوكم"}, {"display": "فَتَسْتَجِيبُونَ", "match": "فتستجيبون"}, {"display": "بِحَمْدِهِ", "match": "بحمده"}, {"display": "وَتَظُنُّونَ", "match": "وتظنون"}, {"display": "إِنْ", "match": "ان"}, {"display": "لَبِثْتُمْ", "match": "لبثتم"}, {"display": "إِلَّا", "match": "الا"}, {"display": "قَلِيلًا", "match": "قليلا"}]}, {"number": 53, "words": [{"display": "وَقُلْ", "match": "وقل"}, {"display": "لِعِبَادِي", "match": "لعبادي"}, {"display": "يَقُولُوا", "match": "يقولوا"}, {"display": "الَّتِي", "match": "التي"}, {"display": "هِيَ", "match": "هي"}, {"display": "أَحْسَنُ", "match": "احسن"}, {"display": "ۚ", "match": ""}, {"display": "إِنَّ", "match": "ان"}, {"display": "الشَّيْطَانَ", "match": "الشيطان"}, {"display": "يَنْزَغُ", "match": "ينزغ"}, {"display": "بَيْنَهُمْ", "match": "بينهم"}, {"display": "ۚ", "match": ""}, {"display": "إِنَّ", "match": "ان"}, {"display": "الشَّيْطَانَ", "match": "الشيطان"}, {"display": "كَانَ", "match": "كان"}, {"display": "لِلْإِنْسَانِ", "match": "للانسان"}, {"display": "عَدُوًّا", "match": "عدوا"}, {"display": "مُبِينًا", "match": "مبينا"}]}, {"number": 54, "words": [{"display": "رَبُّكُمْ", "match": "ربكم"}, {"display": "أَعْلَمُ", "match": "اعلم"}, {"display": "بِكُمْ", "match": "بكم"}, {"display": "ۖ", "match": ""}, {"display": "إِنْ", "match": "ان"}, {"display": "يَشَأْ", "match": "يشا"}, {"display": "يَرْحَمْكُمْ", "match": "يرحمكم"}, {"display": "أَوْ", "match": "او"}, {"display": "إِنْ", "match": "ان"}, {"display": "يَشَأْ", "match": "يشا"}, {"display": "يُعَذِّبْكُمْ", "match": "يعذبكم"}, {"display": "ۚ", "match": ""}, {"display": "وَمَا", "match": "وما"}, {"display": "أَرْسَلْنَاكَ", "match": "ارسلناك"}, {"display": "عَلَيْهِمْ", "match": "عليهم"}, {"display": "وَكِيلًا", "match": "وكيلا"}]}, {"number": 55, "words": [{"display": "وَرَبُّكَ", "match": "وربك"}, {"display": "أَعْلَمُ", "match": "اعلم"}, {"display": "بِمَنْ", "match": "بمن"}, {"display": "فِي", "match": "في"}, {"display": "السَّمَاوَاتِ", "match": "السماوات"}, {"display": "وَالْأَرْضِ", "match": "والارض"}, {"display": "ۗ", "match": ""}, {"display": "وَلَقَدْ", "match": "ولقد"}, {"display": "فَضَّلْنَا", "match": "فضلنا"}, {"display": "بَعْضَ", "match": "بعض"}, {"display": "النَّبِيِّينَ", "match": "النبيين"}, {"display": "عَلَىٰ", "match": "علي"}, {"display": "بَعْضٍ", "match": "بعض"}, {"display": "ۖ", "match": ""}, {"display": "وَآتَيْنَا", "match": "واتينا"}, {"display": "دَاوُودَ", "match": "داوود"}, {"display": "زَبُورًا", "match": "زبورا"}]}, {"number": 56, "words": [{"display": "قُلِ", "match": "قل"}, {"display": "ادْعُوا", "match": "ادعوا"}, {"display": "الَّذِينَ", "match": "الذين"}, {"display": "زَعَمْتُمْ", "match": "زعمتم"}, {"display": "مِنْ", "match": "من"}, {"display": "دُونِهِ", "match": "دونه"}, {"display": "فَلَا", "match": "فلا"}, {"display": "يَمْلِكُونَ", "match": "يملكون"}, {"display": "كَشْفَ", "match": "كشف"}, {"display": "الضُّرِّ", "match": "الضر"}, {"display": "عَنْكُمْ", "match": "عنكم"}, {"display": "وَلَا", "match": "ولا"}, {"display": "تَحْوِيلًا", "match": "تحويلا"}]}, {"number": 57, "words": [{"display": "أُولَٰئِكَ", "match": "اولئك"}, {"display": "الَّذِينَ", "match": "الذين"}, {"display": "يَدْعُونَ", "match": "يدعون"}, {"display": "يَبْتَغُونَ", "match": "يبتغون"}, {"display": "إِلَىٰ", "match": "الي"}, {"display": "رَبِّهِمُ", "match": "ربهم"}, {"display": "الْوَسِيلَةَ", "match": "الوسيله"}, {"display": "أَيُّهُمْ", "match": "ايهم"}, {"display": "أَقْرَبُ", "match": "اقرب"}, {"display": "وَيَرْجُونَ", "match": "ويرجون"}, {"display": "رَحْمَتَهُ", "match": "رحمته"}, {"display": "وَيَخَافُونَ", "match": "ويخافون"}, {"display": "عَذَابَهُ", "match": "عذابه"}, {"display": "ۚ", "match": ""}, {"display": "إِنَّ", "match": "ان"}, {"display": "عَذَابَ", "match": "عذاب"}, {"display": "رَبِّكَ", "match": "ربك"}, {"display": "كَانَ", "match": "كان"}, {"display": "مَحْذُورًا", "match": "محذورا"}]}, {"number": 58, "words": [{"display": "وَإِنْ", "match": "وان"}, {"display": "مِنْ", "match": "من"}, {"display": "قَرْيَةٍ", "match": "قريه"}, {"display": "إِلَّا", "match": "الا"}, {"display": "نَحْنُ", "match": "نحن"}, {"display": "مُهْلِكُوهَا", "match": "مهلكوها"}, {"display": "قَبْلَ", "match": "قبل"}, {"display": "يَوْمِ", "match": "يوم"}, {"display": "الْقِيَامَةِ", "match": "القيامه"}, {"display": "أَوْ", "match": "او"}, {"display": "مُعَذِّبُوهَا", "match": "معذبوها"}, {"display": "عَذَابًا", "match": "عذابا"}, {"display": "شَدِيدًا", "match": "شديدا"}, {"display": "ۚ", "match": ""}, {"display": "كَانَ", "match": "كان"}, {"display": "ذَٰلِكَ", "match": "ذلك"}, {"display": "فِي", "match": "في"}, {"display": "الْكِتَابِ", "match": "الكتاب"}, {"display": "مَسْطُورًا", "match": "مسطورا"}]}, {"number": 59, "words": [{"display": "وَمَا", "match": "وما"}, {"display": "مَنَعَنَا", "match": "منعنا"}, {"display": "أَنْ", "match": "ان"}, {"display": "نُرْسِلَ", "match": "نرسل"}, {"display": "بِالْآيَاتِ", "match": "بالايات"}, {"display": "إِلَّا", "match": "الا"}, {"display": "أَنْ", "match": "ان"}, {"display": "كَذَّبَ", "match": "كذب"}, {"display": "بِهَا", "match": "بها"}, {"display": "الْأَوَّلُونَ", "match": "الاولون"}, {"display": "ۚ", "match": ""}, {"display": "وَآتَيْنَا", "match": "واتينا"}, {"display": "ثَمُودَ", "match": "ثمود"}, {"display": "النَّاقَةَ", "match": "الناقه"}, {"display": "مُبْصِرَةً", "match": "مبصره"}, {"display": "فَظَلَمُوا", "match": "فظلموا"}, {"display": "بِهَا", "match": "بها"}, {"display": "ۚ", "match": ""}, {"display": "وَمَا", "match": "وما"}, {"display": "نُرْسِلُ", "match": "نرسل"}, {"display": "بِالْآيَاتِ", "match": "بالايات"}, {"display": "إِلَّا", "match": "الا"}, {"display": "تَخْوِيفًا", "match": "تخويفا"}]}, {"number": 60, "words": [{"display": "وَإِذْ", "match": "واذ"}, {"display": "قُلْنَا", "match": "قلنا"}, {"display": "لَكَ", "match": "لك"}, {"display": "إِنَّ", "match": "ان"}, {"display": "رَبَّكَ", "match": "ربك"}, {"display": "أَحَاطَ", "match": "احاط"}, {"display": "بِالنَّاسِ", "match": "بالناس"}, {"display": "ۚ", "match": ""}, {"display": "وَمَا", "match": "وما"}, {"display": "جَعَلْنَا", "match": "جعلنا"}, {"display": "الرُّؤْيَا", "match": "الرؤيا"}, {"display": "الَّتِي", "match": "التي"}, {"display": "أَرَيْنَاكَ", "match": "اريناك"}, {"display": "إِلَّا", "match": "الا"}, {"display": "فِتْنَةً", "match": "فتنه"}, {"display": "لِلنَّاسِ", "match": "للناس"}, {"display": "وَالشَّجَرَةَ", "match": "والشجره"}, {"display": "الْمَلْعُونَةَ", "match": "الملعونه"}, {"display": "فِي", "match": "في"}, {"display": "الْقُرْآنِ", "match": "القران"}, {"display": "ۚ", "match": ""}, {"display": "وَنُخَوِّفُهُمْ", "match": "ونخوفهم"}, {"display": "فَمَا", "match": "فما"}, {"display": "يَزِيدُهُمْ", "match": "يزيدهم"}, {"display": "إِلَّا", "match": "الا"}, {"display": "طُغْيَانًا", "match": "طغيانا"}, {"display": "كَبِيرًا", "match": "كبيرا"}]}, {"number": 61, "words": [{"display": "وَإِذْ", "match": "واذ"}, {"display": "قُلْنَا", "match": "قلنا"}, {"display": "لِلْمَلَائِكَةِ", "match": "للملائكه"}, {"display": "اسْجُدُوا", "match": "اسجدوا"}, {"display": "لِآدَمَ", "match": "لادم"}, {"display": "فَسَجَدُوا", "match": "فسجدوا"}, {"display": "إِلَّا", "match": "الا"}, {"display": "إِبْلِيسَ", "match": "ابليس"}, {"display": "قَالَ", "match": "قال"}, {"display": "أَأَسْجُدُ", "match": "ااسجد"}, {"display": "لِمَنْ", "match": "لمن"}, {"display": "خَلَقْتَ", "match": "خلقت"}, {"display": "طِينًا", "match": "طينا"}]}, {"number": 62, "words": [{"display": "قَالَ", "match": "قال"}, {"display": "أَرَأَيْتَكَ", "match": "ارايتك"}, {"display": "هَٰذَا", "match": "هذا"}, {"display": "الَّذِي", "match": "الذي"}, {"display": "كَرَّمْتَ", "match": "كرمت"}, {"display": "عَلَيَّ", "match": "علي"}, {"display": "لَئِنْ", "match": "لئن"}, {"display": "أَخَّرْتَنِ", "match": "اخرتن"}, {"display": "إِلَىٰ", "match": "الي"}, {"display": "يَوْمِ", "match": "يوم"}, {"display": "الْقِيَامَةِ", "match": "القيامه"}, {"display": "لَأَحْتَنِكَنَّ", "match": "لاحتنكن"}, {"display": "ذُرِّيَّتَهُ", "match": "ذريته"}, {"display": "إِلَّا", "match": "الا"}, {"display": "قَلِيلًا", "match": "قليلا"}]}, {"number": 63, "words": [{"display": "قَالَ", "match": "قال"}, {"display": "اذْهَبْ", "match": "اذهب"}, {"display": "فَمَنْ", "match": "فمن"}, {"display": "تَبِعَكَ", "match": "تبعك"}, {"display": "مِنْهُمْ", "match": "منهم"}, {"display": "فَإِنَّ", "match": "فان"}, {"display": "جَهَنَّمَ", "match": "جهنم"}, {"display": "جَزَاؤُكُمْ", "match": "جزاؤكم"}, {"display": "جَزَاءً", "match": "جزاء"}, {"display": "مَوْفُورًا", "match": "موفورا"}]}, {"number": 64, "words": [{"display": "وَاسْتَفْزِزْ", "match": "واستفزز"}, {"display": "مَنِ", "match": "من"}, {"display": "اسْتَطَعْتَ", "match": "استطعت"}, {"display": "مِنْهُمْ", "match": "منهم"}, {"display": "بِصَوْتِكَ", "match": "بصوتك"}, {"display": "وَأَجْلِبْ", "match": "واجلب"}, {"display": "عَلَيْهِمْ", "match": "عليهم"}, {"display": "بِخَيْلِكَ", "match": "بخيلك"}, {"display": "وَرَجِلِكَ", "match": "ورجلك"}, {"display": "وَشَارِكْهُمْ", "match": "وشاركهم"}, {"display": "فِي", "match": "في"}, {"display": "الْأَمْوَالِ", "match": "الاموال"}, {"display": "وَالْأَوْلَادِ", "match": "والاولاد"}, {"display": "وَعِدْهُمْ", "match": "وعدهم"}, {"display": "ۚ", "match": ""}, {"display": "وَمَا", "match": "وما"}, {"display": "يَعِدُهُمُ", "match": "يعدهم"}, {"display": "الشَّيْطَانُ", "match": "الشيطان"}, {"display": "إِلَّا", "match": "الا"}, {"display": "غُرُورًا", "match": "غرورا"}]}, {"number": 65, "words": [{"display": "إِنَّ", "match": "ان"}, {"display": "عِبَادِي", "match": "عبادي"}, {"display": "لَيْسَ", "match": "ليس"}, {"display": "لَكَ", "match": "لك"}, {"display": "عَلَيْهِمْ", "match": "عليهم"}, {"display": "سُلْطَانٌ", "match": "سلطان"}, {"display": "ۚ", "match": ""}, {"display": "وَكَفَىٰ", "match": "وكفي"}, {"display": "بِرَبِّكَ", "match": "بربك"}, {"display": "وَكِيلًا", "match": "وكيلا"}]}, {"number": 66, "words": [{"display": "رَبُّكُمُ", "match": "ربكم"}, {"display": "الَّذِي", "match": "الذي"}, {"display": "يُزْجِي", "match": "يزجي"}, {"display": "لَكُمُ", "match": "لكم"}, {"display": "الْفُلْكَ", "match": "الفلك"}, {"display": "فِي", "match": "في"}, {"display": "الْبَحْرِ", "match": "البحر"}, {"display": "لِتَبْتَغُوا", "match": "لتبتغوا"}, {"display": "مِنْ", "match": "من"}, {"display": "فَضْلِهِ", "match": "فضله"}, {"display": "ۚ", "match": ""}, {"display": "إِنَّهُ", "match": "انه"}, {"display": "كَانَ", "match": "كان"}, {"display": "بِكُمْ", "match": "بكم"}, {"display": "رَحِيمًا", "match": "رحيما"}]}, {"number": 67, "words": [{"display": "وَإِذَا", "match": "واذا"}, {"display": "مَسَّكُمُ", "match": "مسكم"}, {"display": "الضُّرُّ", "match": "الضر"}, {"display": "فِي", "match": "في"}, {"display": "الْبَحْرِ", "match": "البحر"}, {"display": "ضَلَّ", "match": "ضل"}, {"display": "مَنْ", "match": "من"}, {"display": "تَدْعُونَ", "match": "تدعون"}, {"display": "إِلَّا", "match": "الا"}, {"display": "إِيَّاهُ", "match": "اياه"}, {"display": "ۖ", "match": ""}, {"display": "فَلَمَّا", "match": "فلما"}, {"display": "نَجَّاكُمْ", "match": "نجاكم"}, {"display": "إِلَى", "match": "الي"}, {"display": "الْبَرِّ", "match": "البر"}, {"display": "أَعْرَضْتُمْ", "match": "اعرضتم"}, {"display": "ۚ", "match": ""}, {"display": "وَكَانَ", "match": "وكان"}, {"display": "الْإِنْسَانُ", "match": "الانسان"}, {"display": "كَفُورًا", "match": "كفورا"}]}, {"number": 68, "words": [{"display": "أَفَأَمِنْتُمْ", "match": "افامنتم"}, {"display": "أَنْ", "match": "ان"}, {"display": "يَخْسِفَ", "match": "يخسف"}, {"display": "بِكُمْ", "match": "بكم"}, {"display": "جَانِبَ", "match": "جانب"}, {"display": "الْبَرِّ", "match": "البر"}, {"display": "أَوْ", "match": "او"}, {"display": "يُرْسِلَ", "match": "يرسل"}, {"display": "عَلَيْكُمْ", "match": "عليكم"}, {"display": "حَاصِبًا", "match": "حاصبا"}, {"display": "ثُمَّ", "match": "ثم"}, {"display": "لَا", "match": "لا"}, {"display": "تَجِدُوا", "match": "تجدوا"}, {"display": "لَكُمْ", "match": "لكم"}, {"display": "وَكِيلًا", "match": "وكيلا"}]}, {"number": 69, "words": [{"display": "أَمْ", "match": "ام"}, {"display": "أَمِنْتُمْ", "match": "امنتم"}, {"display": "أَنْ", "match": "ان"}, {"display": "يُعِيدَكُمْ", "match": "يعيدكم"}, {"display": "فِيهِ", "match": "فيه"}, {"display": "تَارَةً", "match": "تاره"}, {"display": "أُخْرَىٰ", "match": "اخري"}, {"display": "فَيُرْسِلَ", "match": "فيرسل"}, {"display": "عَلَيْكُمْ", "match": "عليكم"}, {"display": "قَاصِفًا", "match": "قاصفا"}, {"display": "مِنَ", "match": "من"}, {"display": "الرِّيحِ", "match": "الريح"}, {"display": "فَيُغْرِقَكُمْ", "match": "فيغرقكم"}, {"display": "بِمَا", "match": "بما"}, {"display": "كَفَرْتُمْ", "match": "كفرتم"}, {"display": "ۙ", "match": ""}, {"display": "ثُمَّ", "match": "ثم"}, {"display": "لَا", "match": "لا"}, {"display": "تَجِدُوا", "match": "تجدوا"}, {"display": "لَكُمْ", "match": "لكم"}, {"display": "عَلَيْنَا", "match": "علينا"}, {"display": "بِهِ", "match": "به"}, {"display": "تَبِيعًا", "match": "تبيعا"}]}, {"number": 70, "words": [{"display": "وَلَقَدْ", "match": "ولقد"}, {"display": "كَرَّمْنَا", "match": "كرمنا"}, {"display": "بَنِي", "match": "بني"}, {"display": "آدَمَ", "match": "ادم"}, {"display": "وَحَمَلْنَاهُمْ", "match": "وحملناهم"}, {"display": "فِي", "match": "في"}, {"display": "الْبَرِّ", "match": "البر"}, {"display": "وَالْبَحْرِ", "match": "والبحر"}, {"display": "وَرَزَقْنَاهُمْ", "match": "ورزقناهم"}, {"display": "مِنَ", "match": "من"}, {"display": "الطَّيِّبَاتِ", "match": "الطيبات"}, {"display": "وَفَضَّلْنَاهُمْ", "match": "وفضلناهم"}, {"display": "عَلَىٰ", "match": "علي"}, {"display": "كَثِيرٍ", "match": "كثير"}, {"display": "مِمَّنْ", "match": "ممن"}, {"display": "خَلَقْنَا", "match": "خلقنا"}, {"display": "تَفْضِيلًا", "match": "تفضيلا"}]}, {"number": 71, "words": [{"display": "يَوْمَ", "match": "يوم"}, {"display": "نَدْعُو", "match": "ندعو"}, {"display": "كُلَّ", "match": "كل"}, {"display": "أُنَاسٍ", "match": "اناس"}, {"display": "بِإِمَامِهِمْ", "match": "بامامهم"}, {"display": "ۖ", "match": ""}, {"display": "فَمَنْ", "match": "فمن"}, {"display": "أُوتِيَ", "match": "اوتي"}, {"display": "كِتَابَهُ", "match": "كتابه"}, {"display": "بِيَمِينِهِ", "match": "بيمينه"}, {"display": "فَأُولَٰئِكَ", "match": "فاولئك"}, {"display": "يَقْرَءُونَ", "match": "يقرءون"}, {"display": "كِتَابَهُمْ", "match": "كتابهم"}, {"display": "وَلَا", "match": "ولا"}, {"display": "يُظْلَمُونَ", "match": "يظلمون"}, {"display": "فَتِيلًا", "match": "فتيلا"}]}, {"number": 72, "words": [{"display": "وَمَنْ", "match": "ومن"}, {"display": "كَانَ", "match": "كان"}, {"display": "فِي", "match": "في"}, {"display": "هَٰذِهِ", "match": "هذه"}, {"display": "أَعْمَىٰ", "match": "اعمي"}, {"display": "فَهُوَ", "match": "فهو"}, {"display": "فِي", "match": "في"}, {"display": "الْآخِرَةِ", "match": "الاخره"}, {"display": "أَعْمَىٰ", "match": "اعمي"}, {"display": "وَأَضَلُّ", "match": "واضل"}, {"display": "سَبِيلًا", "match": "سبيلا"}]}, {"number": 73, "words": [{"display": "وَإِنْ", "match": "وان"}, {"display": "كَادُوا", "match": "كادوا"}, {"display": "لَيَفْتِنُونَكَ", "match": "ليفتنونك"}, {"display": "عَنِ", "match": "عن"}, {"display": "الَّذِي", "match": "الذي"}, {"display": "أَوْحَيْنَا", "match": "اوحينا"}, {"display": "إِلَيْكَ", "match": "اليك"}, {"display": "لِتَفْتَرِيَ", "match": "لتفتري"}, {"display": "عَلَيْنَا", "match": "علينا"}, {"display": "غَيْرَهُ", "match": "غيره"}, {"display": "ۖ", "match": ""}, {"display": "وَإِذًا", "match": "واذا"}, {"display": "لَاتَّخَذُوكَ", "match": "لاتخذوك"}, {"display": "خَلِيلًا", "match": "خليلا"}]}, {"number": 74, "words": [{"display": "وَلَوْلَا", "match": "ولولا"}, {"display": "أَنْ", "match": "ان"}, {"display": "ثَبَّتْنَاكَ", "match": "ثبتناك"}, {"display": "لَقَدْ", "match": "لقد"}, {"display": "كِدْتَ", "match": "كدت"}, {"display": "تَرْكَنُ", "match": "تركن"}, {"display": "إِلَيْهِمْ", "match": "اليهم"}, {"display": "شَيْئًا", "match": "شيئا"}, {"display": "قَلِيلًا", "match": "قليلا"}]}, {"number": 75, "words": [{"display": "إِذًا", "match": "اذا"}, {"display": "لَأَذَقْنَاكَ", "match": "لاذقناك"}, {"display": "ضِعْفَ", "match": "ضعف"}, {"display": "الْحَيَاةِ", "match": "الحياه"}, {"display": "وَضِعْفَ", "match": "وضعف"}, {"display": "الْمَمَاتِ", "match": "الممات"}, {"display": "ثُمَّ", "match": "ثم"}, {"display": "لَا", "match": "لا"}, {"display": "تَجِدُ", "match": "تجد"}, {"display": "لَكَ", "match": "لك"}, {"display": "عَلَيْنَا", "match": "علينا"}, {"display": "نَصِيرًا", "match": "نصيرا"}]}, {"number": 76, "words": [{"display": "وَإِنْ", "match": "وان"}, {"display": "كَادُوا", "match": "كادوا"}, {"display": "لَيَسْتَفِزُّونَكَ", "match": "ليستفزونك"}, {"display": "مِنَ", "match": "من"}, {"display": "الْأَرْضِ", "match": "الارض"}, {"display": "لِيُخْرِجُوكَ", "match": "ليخرجوك"}, {"display": "مِنْهَا", "match": "منها"}, {"display": "ۖ", "match": ""}, {"display": "وَإِذًا", "match": "واذا"}, {"display": "لَا", "match": "لا"}, {"display": "يَلْبَثُونَ", "match": "يلبثون"}, {"display": "خِلَافَكَ", "match": "خلافك"}, {"display": "إِلَّا", "match": "الا"}, {"display": "قَلِيلًا", "match": "قليلا"}]}, {"number": 77, "words": [{"display": "سُنَّةَ", "match": "سنه"}, {"display": "مَنْ", "match": "من"}, {"display": "قَدْ", "match": "قد"}, {"display": "أَرْسَلْنَا", "match": "ارسلنا"}, {"display": "قَبْلَكَ", "match": "قبلك"}, {"display": "مِنْ", "match": "من"}, {"display": "رُسُلِنَا", "match": "رسلنا"}, {"display": "ۖ", "match": ""}, {"display": "وَلَا", "match": "ولا"}, {"display": "تَجِدُ", "match": "تجد"}, {"display": "لِسُنَّتِنَا", "match": "لسنتنا"}, {"display": "تَحْوِيلًا", "match": "تحويلا"}]}, {"number": 78, "words": [{"display": "أَقِمِ", "match": "اقم"}, {"display": "الصَّلَاةَ", "match": "الصلاه"}, {"display": "لِدُلُوكِ", "match": "لدلوك"}, {"display": "الشَّمْسِ", "match": "الشمس"}, {"display": "إِلَىٰ", "match": "الي"}, {"display": "غَسَقِ", "match": "غسق"}, {"display": "اللَّيْلِ", "match": "الليل"}, {"display": "وَقُرْآنَ", "match": "وقران"}, {"display": "الْفَجْرِ", "match": "الفجر"}, {"display": "ۖ", "match": ""}, {"display": "إِنَّ", "match": "ان"}, {"display": "قُرْآنَ", "match": "قران"}, {"display": "الْفَجْرِ", "match": "الفجر"}, {"display": "كَانَ", "match": "كان"}, {"display": "مَشْهُودًا", "match": "مشهودا"}]}, {"number": 79, "words": [{"display": "وَمِنَ", "match": "ومن"}, {"display": "اللَّيْلِ", "match": "الليل"}, {"display": "فَتَهَجَّدْ", "match": "فتهجد"}, {"display": "بِهِ", "match": "به"}, {"display": "نَافِلَةً", "match": "نافله"}, {"display": "لَكَ", "match": "لك"}, {"display": "عَسَىٰ", "match": "عسي"}, {"display": "أَنْ", "match": "ان"}, {"display": "يَبْعَثَكَ", "match": "يبعثك"}, {"display": "رَبُّكَ", "match": "ربك"}, {"display": "مَقَامًا", "match": "مقاما"}, {"display": "مَحْمُودًا", "match": "محمودا"}]}, {"number": 80, "words": [{"display": "وَقُلْ", "match": "وقل"}, {"display": "رَبِّ", "match": "رب"}, {"display": "أَدْخِلْنِي", "match": "ادخلني"}, {"display": "مُدْخَلَ", "match": "مدخل"}, {"display": "صِدْقٍ", "match": "صدق"}, {"display": "وَأَخْرِجْنِي", "match": "واخرجني"}, {"display": "مُخْرَجَ", "match": "مخرج"}, {"display": "صِدْقٍ", "match": "صدق"}, {"display": "وَاجْعَلْ", "match": "واجعل"}, {"display": "لِي", "match": "لي"}, {"display": "مِنْ", "match": "من"}, {"display": "لَدُنْكَ", "match": "لدنك"}, {"display": "سُلْطَانًا", "match": "سلطانا"}, {"display": "نَصِيرًا", "match": "نصيرا"}]}, {"number": 81, "words": [{"display": "وَقُلْ", "match": "وقل"}, {"display": "جَاءَ", "match": "جاء"}, {"display": "الْحَقُّ", "match": "الحق"}, {"display": "وَزَهَقَ", "match": "وزهق"}, {"display": "الْبَاطِلُ", "match": "الباطل"}, {"display": "ۚ", "match": ""}, {"display": "إِنَّ", "match": "ان"}, {"display": "الْبَاطِلَ", "match": "الباطل"}, {"display": "كَانَ", "match": "كان"}, {"display": "زَهُوقًا", "match": "زهوقا"}]}, {"number": 82, "words": [{"display": "وَنُنَزِّلُ", "match": "وننزل"}, {"display": "مِنَ", "match": "من"}, {"display": "الْقُرْآنِ", "match": "القران"}, {"display": "مَا", "match": "ما"}, {"display": "هُوَ", "match": "هو"}, {"display": "شِفَاءٌ", "match": "شفاء"}, {"display": "وَرَحْمَةٌ", "match": "ورحمه"}, {"display": "لِلْمُؤْمِنِينَ", "match": "للمؤمنين"}, {"display": "ۙ", "match": ""}, {"display": "وَلَا", "match": "ولا"}, {"display": "يَزِيدُ", "match": "يزيد"}, {"display": "الظَّالِمِينَ", "match": "الظالمين"}, {"display": "إِلَّا", "match": "الا"}, {"display": "خَسَارًا", "match": "خسارا"}]}, {"number": 83, "words": [{"display": "وَإِذَا", "match": "واذا"}, {"display": "أَنْعَمْنَا", "match": "انعمنا"}, {"display": "عَلَى", "match": "علي"}, {"display": "الْإِنْسَانِ", "match": "الانسان"}, {"display": "أَعْرَضَ", "match": "اعرض"}, {"display": "وَنَأَىٰ", "match": "وناي"}, {"display": "بِجَانِبِهِ", "match": "بجانبه"}, {"display": "ۖ", "match": ""}, {"display": "وَإِذَا", "match": "واذا"}, {"display": "مَسَّهُ", "match": "مسه"}, {"display": "الشَّرُّ", "match": "الشر"}, {"display": "كَانَ", "match": "كان"}, {"display": "يَئُوسًا", "match": "يئوسا"}]}, {"number": 84, "words": [{"display": "قُلْ", "match": "قل"}, {"display": "كُلٌّ", "match": "كل"}, {"display": "يَعْمَلُ", "match": "يعمل"}, {"display": "عَلَىٰ", "match": "علي"}, {"display": "شَاكِلَتِهِ", "match": "شاكلته"}, {"display": "فَرَبُّكُمْ", "match": "فربكم"}, {"display": "أَعْلَمُ", "match": "اعلم"}, {"display": "بِمَنْ", "match": "بمن"}, {"display": "هُوَ", "match": "هو"}, {"display": "أَهْدَىٰ", "match": "اهدي"}, {"display": "سَبِيلًا", "match": "سبيلا"}]}, {"number": 85, "words": [{"display": "وَيَسْأَلُونَكَ", "match": "ويسالونك"}, {"display": "عَنِ", "match": "عن"}, {"display": "الرُّوحِ", "match": "الروح"}, {"display": "ۖ", "match": ""}, {"display": "قُلِ", "match": "قل"}, {"display": "الرُّوحُ", "match": "الروح"}, {"display": "مِنْ", "match": "من"}, {"display": "أَمْرِ", "match": "امر"}, {"display": "رَبِّي", "match": "ربي"}, {"display": "وَمَا", "match": "وما"}, {"display": "أُوتِيتُمْ", "match": "اوتيتم"}, {"display": "مِنَ", "match": "من"}, {"display": "الْعِلْمِ", "match": "العلم"}, {"display": "إِلَّا", "match": "الا"}, {"display": "قَلِيلًا", "match": "قليلا"}]}, {"number": 86, "words": [{"display": "وَلَئِنْ", "match": "ولئن"}, {"display": "شِئْنَا", "match": "شئنا"}, {"display": "لَنَذْهَبَنَّ", "match": "لنذهبن"}, {"display": "بِالَّذِي", "match": "بالذي"}, {"display": "أَوْحَيْنَا", "match": "اوحينا"}, {"display": "إِلَيْكَ", "match": "اليك"}, {"display": "ثُمَّ", "match": "ثم"}, {"display": "لَا", "match": "لا"}, {"display": "تَجِدُ", "match": "تجد"}, {"display": "لَكَ", "match": "لك"}, {"display": "بِهِ", "match": "به"}, {"display": "عَلَيْنَا", "match": "علينا"}, {"display": "وَكِيلًا", "match": "وكيلا"}]}, {"number": 87, "words": [{"display": "إِلَّا", "match": "الا"}, {"display": "رَحْمَةً", "match": "رحمه"}, {"display": "مِنْ", "match": "من"}, {"display": "رَبِّكَ", "match": "ربك"}, {"display": "ۚ", "match": ""}, {"display": "إِنَّ", "match": "ان"}, {"display": "فَضْلَهُ", "match": "فضله"}, {"display": "كَانَ", "match": "كان"}, {"display": "عَلَيْكَ", "match": "عليك"}, {"display": "كَبِيرًا", "match": "كبيرا"}]}, {"number": 88, "words": [{"display": "قُلْ", "match": "قل"}, {"display": "لَئِنِ", "match": "لئن"}, {"display": "اجْتَمَعَتِ", "match": "اجتمعت"}, {"display": "الْإِنْسُ", "match": "الانس"}, {"display": "وَالْجِنُّ", "match": "والجن"}, {"display": "عَلَىٰ", "match": "علي"}, {"display": "أَنْ", "match": "ان"}, {"display": "يَأْتُوا", "match": "ياتوا"}, {"display": "بِمِثْلِ", "match": "بمثل"}, {"display": "هَٰذَا", "match": "هذا"}, {"display": "الْقُرْآنِ", "match": "القران"}, {"display": "لَا", "match": "لا"}, {"display": "يَأْتُونَ", "match": "ياتون"}, {"display": "بِمِثْلِهِ", "match": "بمثله"}, {"display": "وَلَوْ", "match": "ولو"}, {"display": "كَانَ", "match": "كان"}, {"display": "بَعْضُهُمْ", "match": "بعضهم"}, {"display": "لِبَعْضٍ", "match": "لبعض"}, {"display": "ظَهِيرًا", "match": "ظهيرا"}]}, {"number": 89, "words": [{"display": "وَلَقَدْ", "match": "ولقد"}, {"display": "صَرَّفْنَا", "match": "صرفنا"}, {"display": "لِلنَّاسِ", "match": "للناس"}, {"display": "فِي", "match": "في"}, {"display": "هَٰذَا", "match": "هذا"}, {"display": "الْقُرْآنِ", "match": "القران"}, {"display": "مِنْ", "match": "من"}, {"display": "كُلِّ", "match": "كل"}, {"display": "مَثَلٍ", "match": "مثل"}, {"display": "فَأَبَىٰ", "match": "فابي"}, {"display": "أَكْثَرُ", "match": "اكثر"}, {"display": "النَّاسِ", "match": "الناس"}, {"display": "إِلَّا", "match": "الا"}, {"display": "كُفُورًا", "match": "كفورا"}]}, {"number": 90, "words": [{"display": "وَقَالُوا", "match": "وقالوا"}, {"display": "لَنْ", "match": "لن"}, {"display": "نُؤْمِنَ", "match": "نؤمن"}, {"display": "لَكَ", "match": "لك"}, {"display": "حَتَّىٰ", "match": "حتي"}, {"display": "تَفْجُرَ", "match": "تفجر"}, {"display": "لَنَا", "match": "لنا"}, {"display": "مِنَ", "match": "من"}, {"display": "الْأَرْضِ", "match": "الارض"}, {"display": "يَنْبُوعًا", "match": "ينبوعا"}]}, {"number": 91, "words": [{"display": "أَوْ", "match": "او"}, {"display": "تَكُونَ", "match": "تكون"}, {"display": "لَكَ", "match": "لك"}, {"display": "جَنَّةٌ", "match": "جنه"}, {"display": "مِنْ", "match": "من"}, {"display": "نَخِيلٍ", "match": "نخيل"}, {"display": "وَعِنَبٍ", "match": "وعنب"}, {"display": "فَتُفَجِّرَ", "match": "فتفجر"}, {"display": "الْأَنْهَارَ", "match": "الانهار"}, {"display": "خِلَالَهَا", "match": "خلالها"}, {"display": "تَفْجِيرًا", "match": "تفجيرا"}]}, {"number": 92, "words": [{"display": "أَوْ", "match": "او"}, {"display": "تُسْقِطَ", "match": "تسقط"}, {"display": "السَّمَاءَ", "match": "السماء"}, {"display": "كَمَا", "match": "كما"}, {"display": "زَعَمْتَ", "match": "زعمت"}, {"display": "عَلَيْنَا", "match": "علينا"}, {"display": "كِسَفًا", "match": "كسفا"}, {"display": "أَوْ", "match": "او"}, {"display": "تَأْتِيَ", "match": "تاتي"}, {"display": "بِاللَّهِ", "match": "بالله"}, {"display": "وَالْمَلَائِكَةِ", "match": "والملائكه"}, {"display": "قَبِيلًا", "match": "قبيلا"}]}, {"number": 93, "words": [{"display": "أَوْ", "match": "او"}, {"display": "يَكُونَ", "match": "يكون"}, {"display": "لَكَ", "match": "لك"}, {"display": "بَيْتٌ", "match": "بيت"}, {"display": "مِنْ", "match": "من"}, {"display": "زُخْرُفٍ", "match": "زخرف"}, {"display": "أَوْ", "match": "او"}, {"display": "تَرْقَىٰ", "match": "ترقي"}, {"display": "فِي", "match": "في"}, {"display": "السَّمَاءِ", "match": "السماء"}, {"display": "وَلَنْ", "match": "ولن"}, {"display": "نُؤْمِنَ", "match": "نؤمن"}, {"display": "لِرُقِيِّكَ", "match": "لرقيك"}, {"display": "حَتَّىٰ", "match": "حتي"}, {"display": "تُنَزِّلَ", "match": "تنزل"}, {"display": "عَلَيْنَا", "match": "علينا"}, {"display": "كِتَابًا", "match": "كتابا"}, {"display": "نَقْرَؤُهُ", "match": "نقرؤه"}, {"display": "ۗ", "match": ""}, {"display": "قُلْ", "match": "قل"}, {"display": "سُبْحَانَ", "match": "سبحان"}, {"display": "رَبِّي", "match": "ربي"}, {"display": "هَلْ", "match": "هل"}, {"display": "كُنْتُ", "match": "كنت"}, {"display": "إِلَّا", "match": "الا"}, {"display": "بَشَرًا", "match": "بشرا"}, {"display": "رَسُولًا", "match": "رسولا"}]}, {"number": 94, "words": [{"display": "وَمَا", "match": "وما"}, {"display": "مَنَعَ", "match": "منع"}, {"display": "النَّاسَ", "match": "الناس"}, {"display": "أَنْ", "match": "ان"}, {"display": "يُؤْمِنُوا", "match": "يؤمنوا"}, {"display": "إِذْ", "match": "اذ"}, {"display": "جَاءَهُمُ", "match": "جاءهم"}, {"display": "الْهُدَىٰ", "match": "الهدي"}, {"display": "إِلَّا", "match": "الا"}, {"display": "أَنْ", "match": "ان"}, {"display": "قَالُوا", "match": "قالوا"}, {"display": "أَبَعَثَ", "match": "ابعث"}, {"display": "اللَّهُ", "match": "الله"}, {"display": "بَشَرًا", "match": "بشرا"}, {"display": "رَسُولًا", "match": "رسولا"}]}, {"number": 95, "words": [{"display": "قُلْ", "match": "قل"}, {"display": "لَوْ", "match": "لو"}, {"display": "كَانَ", "match": "كان"}, {"display": "فِي", "match": "في"}, {"display": "الْأَرْضِ", "match": "الارض"}, {"display": "مَلَائِكَةٌ", "match": "ملائكه"}, {"display": "يَمْشُونَ", "match": "يمشون"}, {"display": "مُطْمَئِنِّينَ", "match": "مطمئنين"}, {"display": "لَنَزَّلْنَا", "match": "لنزلنا"}, {"display": "عَلَيْهِمْ", "match": "عليهم"}, {"display": "مِنَ", "match": "من"}, {"display": "السَّمَاءِ", "match": "السماء"}, {"display": "مَلَكًا", "match": "ملكا"}, {"display": "رَسُولًا", "match": "رسولا"}]}, {"number": 96, "words": [{"display": "قُلْ", "match": "قل"}, {"display": "كَفَىٰ", "match": "كفي"}, {"display": "بِاللَّهِ", "match": "بالله"}, {"display": "شَهِيدًا", "match": "شهيدا"}, {"display": "بَيْنِي", "match": "بيني"}, {"display": "وَبَيْنَكُمْ", "match": "وبينكم"}, {"display": "ۚ", "match": ""}, {"display": "إِنَّهُ", "match": "انه"}, {"display": "كَانَ", "match": "كان"}, {"display": "بِعِبَادِهِ", "match": "بعباده"}, {"display": "خَبِيرًا", "match": "خبيرا"}, {"display": "بَصِيرًا", "match": "بصيرا"}]}, {"number": 97, "words": [{"display": "وَمَنْ", "match": "ومن"}, {"display": "يَهْدِ", "match": "يهد"}, {"display": "اللَّهُ", "match": "الله"}, {"display": "فَهُوَ", "match": "فهو"}, {"display": "الْمُهْتَدِ", "match": "المهتد"}, {"display": "ۖ", "match": ""}, {"display": "وَمَنْ", "match": "ومن"}, {"display": "يُضْلِلْ", "match": "يضلل"}, {"display": "فَلَنْ", "match": "فلن"}, {"display": "تَجِدَ", "match": "تجد"}, {"display": "لَهُمْ", "match": "لهم"}, {"display": "أَوْلِيَاءَ", "match": "اولياء"}, {"display": "مِنْ", "match": "من"}, {"display": "دُونِهِ", "match": "دونه"}, {"display": "ۖ", "match": ""}, {"display": "وَنَحْشُرُهُمْ", "match": "ونحشرهم"}, {"display": "يَوْمَ", "match": "يوم"}, {"display": "الْقِيَامَةِ", "match": "القيامه"}, {"display": "عَلَىٰ", "match": "علي"}, {"display": "وُجُوهِهِمْ", "match": "وجوههم"}, {"display": "عُمْيًا", "match": "عميا"}, {"display": "وَبُكْمًا", "match": "وبكما"}, {"display": "وَصُمًّا", "match": "وصما"}, {"display": "ۖ", "match": ""}, {"display": "مَأْوَاهُمْ", "match": "ماواهم"}, {"display": "جَهَنَّمُ", "match": "جهنم"}, {"display": "ۖ", "match": ""}, {"display": "كُلَّمَا", "match": "كلما"}, {"display": "خَبَتْ", "match": "خبت"}, {"display": "زِدْنَاهُمْ", "match": "زدناهم"}, {"display": "سَعِيرًا", "match": "سعيرا"}]}, {"number": 98, "words": [{"display": "ذَٰلِكَ", "match": "ذلك"}, {"display": "جَزَاؤُهُمْ", "match": "جزاؤهم"}, {"display": "بِأَنَّهُمْ", "match": "بانهم"}, {"display": "كَفَرُوا", "match": "كفروا"}, {"display": "بِآيَاتِنَا", "match": "باياتنا"}, {"display": "وَقَالُوا", "match": "وقالوا"}, {"display": "أَإِذَا", "match": "ااذا"}, {"display": "كُنَّا", "match": "كنا"}, {"display": "عِظَامًا", "match": "عظاما"}, {"display": "وَرُفَاتًا", "match": "ورفاتا"}, {"display": "أَإِنَّا", "match": "اانا"}, {"display": "لَمَبْعُوثُونَ", "match": "لمبعوثون"}, {"display": "خَلْقًا", "match": "خلقا"}, {"display": "جَدِيدًا", "match": "جديدا"}]}, {"number": 99, "words": [{"display": "أَوَلَمْ", "match": "اولم"}, {"display": "يَرَوْا", "match": "يروا"}, {"display": "أَنَّ", "match": "ان"}, {"display": "اللَّهَ", "match": "الله"}, {"display": "الَّذِي", "match": "الذي"}, {"display": "خَلَقَ", "match": "خلق"}, {"display": "السَّمَاوَاتِ", "match": "السماوات"}, {"display": "وَالْأَرْضَ", "match": "والارض"}, {"display": "قَادِرٌ", "match": "قادر"}, {"display": "عَلَىٰ", "match": "علي"}, {"display": "أَنْ", "match": "ان"}, {"display": "يَخْلُقَ", "match": "يخلق"}, {"display": "مِثْلَهُمْ", "match": "مثلهم"}, {"display": "وَجَعَلَ", "match": "وجعل"}, {"display": "لَهُمْ", "match": "لهم"}, {"display": "أَجَلًا", "match": "اجلا"}, {"display": "لَا", "match": "لا"}, {"display": "رَيْبَ", "match": "ريب"}, {"display": "فِيهِ", "match": "فيه"}, {"display": "فَأَبَى", "match": "فابي"}, {"display": "الظَّالِمُونَ", "match": "الظالمون"}, {"display": "إِلَّا", "match": "الا"}, {"display": "كُفُورًا", "match": "كفورا"}]}, {"number": 100, "words": [{"display": "قُلْ", "match": "قل"}, {"display": "لَوْ", "match": "لو"}, {"display": "أَنْتُمْ", "match": "انتم"}, {"display": "تَمْلِكُونَ", "match": "تملكون"}, {"display": "خَزَائِنَ", "match": "خزائن"}, {"display": "رَحْمَةِ", "match": "رحمه"}, {"display": "رَبِّي", "match": "ربي"}, {"display": "إِذًا", "match": "اذا"}, {"display": "لَأَمْسَكْتُمْ", "match": "لامسكتم"}, {"display": "خَشْيَةَ", "match": "خشيه"}, {"display": "الْإِنْفَاقِ", "match": "الانفاق"}, {"display": "ۚ", "match": ""}, {"display": "وَكَانَ", "match": "وكان"}, {"display": "الْإِنْسَانُ", "match": "الانسان"}, {"display": "قَتُورًا", "match": "قتورا"}]}, {"number": 101, "words": [{"display": "وَلَقَدْ", "match": "ولقد"}, {"display": "آتَيْنَا", "match": "اتينا"}, {"display": "مُوسَىٰ", "match": "موسي"}, {"display": "تِسْعَ", "match": "تسع"}, {"display": "آيَاتٍ", "match": "ايات"}, {"display": "بَيِّنَاتٍ", "match": "بينات"}, {"display": "ۖ", "match": ""}, {"display": "فَاسْأَلْ", "match": "فاسال"}, {"display": "بَنِي", "match": "بني"}, {"display": "إِسْرَائِيلَ", "match": "اسرائيل"}, {"display": "إِذْ", "match": "اذ"}, {"display": "جَاءَهُمْ", "match": "جاءهم"}, {"display": "فَقَالَ", "match": "فقال"}, {"display": "لَهُ", "match": "له"}, {"display": "فِرْعَوْنُ", "match": "فرعون"}, {"display": "إِنِّي", "match": "اني"}, {"display": "لَأَظُنُّكَ", "match": "لاظنك"}, {"display": "يَا", "match": "يا"}, {"display": "مُوسَىٰ", "match": "موسي"}, {"display": "مَسْحُورًا", "match": "مسحورا"}]}, {"number": 102, "words": [{"display": "قَالَ", "match": "قال"}, {"display": "لَقَدْ", "match": "لقد"}, {"display": "عَلِمْتَ", "match": "علمت"}, {"display": "مَا", "match": "ما"}, {"display": "أَنْزَلَ", "match": "انزل"}, {"display": "هَٰؤُلَاءِ", "match": "هؤلاء"}, {"display": "إِلَّا", "match": "الا"}, {"display": "رَبُّ", "match": "رب"}, {"display": "السَّمَاوَاتِ", "match": "السماوات"}, {"display": "وَالْأَرْضِ", "match": "والارض"}, {"display": "بَصَائِرَ", "match": "بصائر"}, {"display": "وَإِنِّي", "match": "واني"}, {"display": "لَأَظُنُّكَ", "match": "لاظنك"}, {"display": "يَا", "match": "يا"}, {"display": "فِرْعَوْنُ", "match": "فرعون"}, {"display": "مَثْبُورًا", "match": "مثبورا"}]}, {"number": 103, "words": [{"display": "فَأَرَادَ", "match": "فاراد"}, {"display": "أَنْ", "match": "ان"}, {"display": "يَسْتَفِزَّهُمْ", "match": "يستفزهم"}, {"display": "مِنَ", "match": "من"}, {"display": "الْأَرْضِ", "match": "الارض"}, {"display": "فَأَغْرَقْنَاهُ", "match": "فاغرقناه"}, {"display": "وَمَنْ", "match": "ومن"}, {"display": "مَعَهُ", "match": "معه"}, {"display": "جَمِيعًا", "match": "جميعا"}]}, {"number": 104, "words": [{"display": "وَقُلْنَا", "match": "وقلنا"}, {"display": "مِنْ", "match": "من"}, {"display": "بَعْدِهِ", "match": "بعده"}, {"display": "لِبَنِي", "match": "لبني"}, {"display": "إِسْرَائِيلَ", "match": "اسرائيل"}, {"display": "اسْكُنُوا", "match": "اسكنوا"}, {"display": "الْأَرْضَ", "match": "الارض"}, {"display": "فَإِذَا", "match": "فاذا"}, {"display": "جَاءَ", "match": "جاء"}, {"display": "وَعْدُ", "match": "وعد"}, {"display": "الْآخِرَةِ", "match": "الاخره"}, {"display": "جِئْنَا", "match": "جئنا"}, {"display": "بِكُمْ", "match": "بكم"}, {"display": "لَفِيفًا", "match": "لفيفا"}]}, {"number": 105, "words": [{"display": "وَبِالْحَقِّ", "match": "وبالحق"}, {"display": "أَنْزَلْنَاهُ", "match": "انزلناه"}, {"display": "وَبِالْحَقِّ", "match": "وبالحق"}, {"display": "نَزَلَ", "match": "نزل"}, {"display": "ۗ", "match": ""}, {"display": "وَمَا", "match": "وما"}, {"display": "أَرْسَلْنَاكَ", "match": "ارسلناك"}, {"display": "إِلَّا", "match": "الا"}, {"display": "مُبَشِّرًا", "match": "مبشرا"}, {"display": "وَنَذِيرًا", "match": "ونذيرا"}]}, {"number": 106, "words": [{"display": "وَقُرْآنًا", "match": "وقرانا"}, {"display": "فَرَقْنَاهُ", "match": "فرقناه"}, {"display": "لِتَقْرَأَهُ", "match": "لتقراه"}, {"display": "عَلَى", "match": "علي"}, {"display": "النَّاسِ", "match": "الناس"}, {"display": "عَلَىٰ", "match": "علي"}, {"display": "مُكْثٍ", "match": "مكث"}, {"display": "وَنَزَّلْنَاهُ", "match": "ونزلناه"}, {"display": "تَنْزِيلًا", "match": "تنزيلا"}]}, {"number": 107, "words": [{"display": "قُلْ", "match": "قل"}, {"display": "آمِنُوا", "match": "امنوا"}, {"display": "بِهِ", "match": "به"}, {"display": "أَوْ", "match": "او"}, {"display": "لَا", "match": "لا"}, {"display": "تُؤْمِنُوا", "match": "تؤمنوا"}, {"display": "ۚ", "match": ""}, {"display": "إِنَّ", "match": "ان"}, {"display": "الَّذِينَ", "match": "الذين"}, {"display": "أُوتُوا", "match": "اوتوا"}, {"display": "الْعِلْمَ", "match": "العلم"}, {"display": "مِنْ", "match": "من"}, {"display": "قَبْلِهِ", "match": "قبله"}, {"display": "إِذَا", "match": "اذا"}, {"display": "يُتْلَىٰ", "match": "يتلي"}, {"display": "عَلَيْهِمْ", "match": "عليهم"}, {"display": "يَخِرُّونَ", "match": "يخرون"}, {"display": "لِلْأَذْقَانِ", "match": "للاذقان"}, {"display": "سُجَّدًا", "match": "سجدا"}]}, {"number": 108, "words": [{"display": "وَيَقُولُونَ", "match": "ويقولون"}, {"display": "سُبْحَانَ", "match": "سبحان"}, {"display": "رَبِّنَا", "match": "ربنا"}, {"display": "إِنْ", "match": "ان"}, {"display": "كَانَ", "match": "كان"}, {"display": "وَعْدُ", "match": "وعد"}, {"display": "رَبِّنَا", "match": "ربنا"}, {"display": "لَمَفْعُولًا", "match": "لمفعولا"}]}, {"number": 109, "words": [{"display": "وَيَخِرُّونَ", "match": "ويخرون"}, {"display": "لِلْأَذْقَانِ", "match": "للاذقان"}, {"display": "يَبْكُونَ", "match": "يبكون"}, {"display": "وَيَزِيدُهُمْ", "match": "ويزيدهم"}, {"display": "خُشُوعًا", "match": "خشوعا"}, {"display": "۩", "match": ""}]}, {"number": 110, "words": [{"display": "قُلِ", "match": "قل"}, {"display": "ادْعُوا", "match": "ادعوا"}, {"display": "اللَّهَ", "match": "الله"}, {"display": "أَوِ", "match": "او"}, {"display": "ادْعُوا", "match": "ادعوا"}, {"display": "الرَّحْمَٰنَ", "match": "الرحمن"}, {"display": "ۖ", "match": ""}, {"display": "أَيًّا", "match": "ايا"}, {"display": "مَا", "match": "ما"}, {"display": "تَدْعُوا", "match": "تدعوا"}, {"display": "فَلَهُ", "match": "فله"}, {"display": "الْأَسْمَاءُ", "match": "الاسماء"}, {"display": "الْحُسْنَىٰ", "match": "الحسني"}, {"display": "ۚ", "match": ""}, {"display": "وَلَا", "match": "ولا"}, {"display": "تَجْهَرْ", "match": "تجهر"}, {"display": "بِصَلَاتِكَ", "match": "بصلاتك"}, {"display": "وَلَا", "match": "ولا"}, {"display": "تُخَافِتْ", "match": "تخافت"}, {"display": "بِهَا", "match": "بها"}, {"display": "وَابْتَغِ", "match": "وابتغ"}, {"display": "بَيْنَ", "match": "بين"}, {"display": "ذَٰلِكَ", "match": "ذلك"}, {"display": "سَبِيلًا", "match": "سبيلا"}]}, {"number": 111, "words": [{"display": "وَقُلِ", "match": "وقل"}, {"display": "الْحَمْدُ", "match": "الحمد"}, {"display": "لِلَّهِ", "match": "لله"}, {"display": "الَّذِي", "match": "الذي"}, {"display": "لَمْ", "match": "لم"}, {"display": "يَتَّخِذْ", "match": "يتخذ"}, {"display": "وَلَدًا", "match": "ولدا"}, {"display": "وَلَمْ", "match": "ولم"}, {"display": "يَكُنْ", "match": "يكن"}, {"display": "لَهُ", "match": "له"}, {"display": "شَرِيكٌ", "match": "شريك"}, {"display": "فِي", "match": "في"}, {"display": "الْمُلْكِ", "match": "الملك"}, {"display": "وَلَمْ", "match": "ولم"}, {"display": "يَكُنْ", "match": "يكن"}, {"display": "لَهُ", "match": "له"}, {"display": "وَلِيٌّ", "match": "ولي"}, {"display": "مِنَ", "match": "من"}, {"display": "الذُّلِّ", "match": "الذل"}, {"display": "ۖ", "match": ""}, {"display": "وَكَبِّرْهُ", "match": "وكبره"}, {"display": "تَكْبِيرًا", "match": "تكبيرا"}]}]}